nft_market/__init__.py
nft_market/market.py
nft_market/nftinfo.py
nft_market/retriever.py
nft_market-1.55.dist-info/LICENSE
nft_market-1.55.dist-info/METADATA
nft_market-1.55.dist-info/WHEEL
nft_market-1.55.dist-info/top_level.txt
nft_market-1.55.dist-info/RECORD
