Metadata-Version: 2.1
Name: nft-market
Version: 1.55
Summary: NFT market is in your hands.
Home-page: https://github.com/ukaznil/nft-market
Author: ukaznil
Author-email: ukaznil@gmail.com
License: UNKNOWN
Project-URL: Bug Tracker, https://github.com/ukaznil/nft-market/issues
Platform: UNKNOWN
Classifier: Programming Language :: Python :: 3
Classifier: License :: OSI Approved :: MIT License
Classifier: Operating System :: OS Independent
Requires-Python: >=3.6
Requires-Dist: selenium
Requires-Dist: webdriver-manager
